{
    "AX": {
        "error": 0.05241266199387112, 
        "fit": "average", 
        "value": -0.07463119716307949
    }, 
    "CDD": {
        "error": 0.00019906903249492837, 
        "fit": "average", 
        "value": 0.00023046648614884666
    }, 
    "H1": {
        "error": 0.09686490586820452, 
        "fit": "average", 
        "value": -0.008420141759935567
    }, 
    "H2": {
        "error": 0.0792033162420303, 
        "fit": "average", 
        "value": -0.04357738120926787
    }, 
    "L1": {
        "error": 0.09929170684538888, 
        "fit": "average", 
        "value": -0.09491088355144743
    }, 
    "L2": {
        "error": 0.12055491005561757, 
        "fit": "average", 
        "value": -0.034811015583260954
    }
}