{
    "Ar36": {
        "error": 0.016420147682686938, 
        "fit": "Parabolic", 
        "value": 2.3061333323209672
    }, 
    "Ar37": {
        "error": 0.20425362662636426, 
        "fit": "linear", 
        "value": 197.82704643739578
    }, 
    "Ar38": {
        "error": 0.10120345362280758, 
        "fit": "linear", 
        "value": 1.8764278548588931
    }, 
    "Ar39": {
        "error": 0.084713498812818352, 
        "fit": "Parabolic", 
        "value": 52.838548859746723
    }, 
    "Ar40": {
        "error": 0.30038864890794575, 
        "fit": "Parabolic", 
        "value": 687.7049995137636
    }, 
    "Ar41": {
        "error": 0.10478185842843007, 
        "fit": "linear", 
        "value": 0.0042418143376325643
    }
}