{
    "AX": {
        "error": 0.00495517428980132, 
        "filter_outliers_dict": {
            "filter_outliers": true, 
            "iterations": 1, 
            "std_devs": 2
        }, 
        "fit": "average", 
        "value": -0.03135138386466183
    }, 
    "CDD": {
        "error": 4.2929812258899455e-06, 
        "filter_outliers_dict": {
            "filter_outliers": true, 
            "iterations": 1, 
            "std_devs": 10
        }, 
        "fit": "average", 
        "value": 1.3579843267607958e-05
    }, 
    "H1": {
        "error": 0.0032778653766257953, 
        "filter_outliers_dict": {
            "filter_outliers": true, 
            "iterations": 1, 
            "std_devs": 2
        }, 
        "fit": "average", 
        "value": -0.026954602744686234
    }, 
    "H2": {
        "error": 0.0032799439482918058, 
        "filter_outliers_dict": {
            "filter_outliers": true, 
            "iterations": 1, 
            "std_devs": 2
        }, 
        "fit": "average", 
        "value": -0.17254524626929235
    }, 
    "L1": {
        "error": 0.0018357678297413829, 
        "filter_outliers_dict": {
            "filter_outliers": true, 
            "iterations": 1, 
            "std_devs": 2
        }, 
        "fit": "average", 
        "value": -0.019852612099304542
    }, 
    "L2": {
        "error": 0.004389639130777468, 
        "filter_outliers_dict": {
            "filter_outliers": true, 
            "iterations": 1, 
            "std_devs": 2
        }, 
        "fit": "average", 
        "value": -0.0167577916619292
    }
}